picod.py
picod-0.0.6.0.dist-info/LICENCE
picod-0.0.6.0.dist-info/METADATA
picod-0.0.6.0.dist-info/WHEEL
picod-0.0.6.0.dist-info/top_level.txt
picod-0.0.6.0.dist-info/RECORD
