Metadata-Version: 2.1
Name: picod
Version: 0.0.6.0
Summary: Raspberry Pi pico module
Home-page: http://abyz.me.uk/picod/py_picod.html
Author: joan
Author-email: joan@abyz.me.uk
Maintainer: joan
Maintainer-email: joan@abyz.me.uk
License: unlicense.org
Download-URL: http://abyz.me.uk/picod/picod.zip
Keywords: gpio,i2c,serial,spi,pwm,servo
Platform: UNKNOWN
Classifier: Programming Language :: Python :: 2
Classifier: Programming Language :: Python :: 3
